{
  "openapi": "3.0.1",
  "info": {
    "title": "ECommerce.UI",
    "version": "1.0"
  },
  "paths": {
    "/api/Account/Register": {
      "post": {
        "tags": [
          "Account"
        ],
        "requestBody": {
          "content": {
            "application/json": {
              "schema": {
                "$ref": "#/components/schemas/RegisterDTO"
              }
            },
            "text/json": {
              "schema": {
                "$ref": "#/components/schemas/RegisterDTO"
              }
            },
            "application/*+json": {
              "schema": {
                "$ref": "#/components/schemas/RegisterDTO"
              }
            }
          }
        },
        "responses": {
          "200": {
            "description": "Success"
          },
          "400": {
            "description": "Bad Request",
            "content": {
              "text/plain": {
                "schema": {
                  "$ref": "#/components/schemas/ProblemDetails"
                }
              },
              "application/json": {
                "schema": {
                  "$ref": "#/components/schemas/ProblemDetails"
                }
              },
              "text/json": {
                "schema": {
                  "$ref": "#/components/schemas/ProblemDetails"
                }
              }
            }
          }
        }
      }
    },
    "/api/Account/Login": {
      "post": {
        "tags": [
          "Account"
        ],
        "requestBody": {
          "content": {
            "application/json": {
              "schema": {
                "$ref": "#/components/schemas/LoginDTO"
              }
            },
            "text/json": {
              "schema": {
                "$ref": "#/components/schemas/LoginDTO"
              }
            },
            "application/*+json": {
              "schema": {
                "$ref": "#/components/schemas/LoginDTO"
              }
            }
          }
        },
        "responses": {
          "200": {
            "description": "Success"
          },
          "400": {
            "description": "Bad Request",
            "content": {
              "text/plain": {
                "schema": {
                  "$ref": "#/components/schemas/ProblemDetails"
                }
              },
              "application/json": {
                "schema": {
                  "$ref": "#/components/schemas/ProblemDetails"
                }
              },
              "text/json": {
                "schema": {
                  "$ref": "#/components/schemas/ProblemDetails"
                }
              }
            }
          }
        }
      }
    },
    "/api/Account/ConfirmEmail": {
      "get": {
        "tags": [
          "Account"
        ],
        "parameters": [
          {
            "name": "userEmail",
            "in": "query",
            "style": "form",
            "schema": {
              "type": "string"
            }
          },
          {
            "name": "Token",
            "in": "query",
            "style": "form",
            "schema": {
              "type": "string"
            }
          }
        ],
        "responses": {
          "200": {
            "description": "Success"
          },
          "400": {
            "description": "Bad Request",
            "content": {
              "text/plain": {
                "schema": {
                  "$ref": "#/components/schemas/ProblemDetails"
                }
              },
              "application/json": {
                "schema": {
                  "$ref": "#/components/schemas/ProblemDetails"
                }
              },
              "text/json": {
                "schema": {
                  "$ref": "#/components/schemas/ProblemDetails"
                }
              }
            }
          }
        }
      }
    },
    "/api/Account/ReConfirmEmail": {
      "get": {
        "tags": [
          "Account"
        ],
        "parameters": [
          {
            "name": "Email",
            "in": "query",
            "style": "form",
            "schema": {
              "type": "string"
            }
          }
        ],
        "responses": {
          "200": {
            "description": "Success"
          },
          "400": {
            "description": "Bad Request",
            "content": {
              "text/plain": {
                "schema": {
                  "$ref": "#/components/schemas/ProblemDetails"
                }
              },
              "application/json": {
                "schema": {
                  "$ref": "#/components/schemas/ProblemDetails"
                }
              },
              "text/json": {
                "schema": {
                  "$ref": "#/components/schemas/ProblemDetails"
                }
              }
            }
          }
        }
      }
    },
    "/api/Account/UserInfo": {
      "get": {
        "tags": [
          "Account"
        ],
        "responses": {
          "200": {
            "description": "Success"
          },
          "401": {
            "description": "Unauthorized",
            "content": {
              "text/plain": {
                "schema": {
                  "$ref": "#/components/schemas/ProblemDetails"
                }
              },
              "application/json": {
                "schema": {
                  "$ref": "#/components/schemas/ProblemDetails"
                }
              },
              "text/json": {
                "schema": {
                  "$ref": "#/components/schemas/ProblemDetails"
                }
              }
            }
          },
          "404": {
            "description": "Not Found",
            "content": {
              "text/plain": {
                "schema": {
                  "$ref": "#/components/schemas/ProblemDetails"
                }
              },
              "application/json": {
                "schema": {
                  "$ref": "#/components/schemas/ProblemDetails"
                }
              },
              "text/json": {
                "schema": {
                  "$ref": "#/components/schemas/ProblemDetails"
                }
              }
            }
          }
        }
      }
    },
    "/api/Account/EditUerProfile": {
      "put": {
        "tags": [
          "Account"
        ],
        "requestBody": {
          "content": {
            "application/json": {
              "schema": {
                "$ref": "#/components/schemas/ChangeUserInfoDTO"
              }
            },
            "text/json": {
              "schema": {
                "$ref": "#/components/schemas/ChangeUserInfoDTO"
              }
            },
            "application/*+json": {
              "schema": {
                "$ref": "#/components/schemas/ChangeUserInfoDTO"
              }
            }
          }
        },
        "responses": {
          "200": {
            "description": "Success"
          },
          "401": {
            "description": "Unauthorized",
            "content": {
              "text/plain": {
                "schema": {
                  "$ref": "#/components/schemas/ProblemDetails"
                }
              },
              "application/json": {
                "schema": {
                  "$ref": "#/components/schemas/ProblemDetails"
                }
              },
              "text/json": {
                "schema": {
                  "$ref": "#/components/schemas/ProblemDetails"
                }
              }
            }
          },
          "404": {
            "description": "Not Found",
            "content": {
              "text/plain": {
                "schema": {
                  "$ref": "#/components/schemas/ProblemDetails"
                }
              },
              "application/json": {
                "schema": {
                  "$ref": "#/components/schemas/ProblemDetails"
                }
              },
              "text/json": {
                "schema": {
                  "$ref": "#/components/schemas/ProblemDetails"
                }
              }
            }
          },
          "500": {
            "description": "Server Error"
          }
        }
      }
    },
    "/api/Account/ChangeEmail": {
      "patch": {
        "tags": [
          "Account"
        ],
        "parameters": [
          {
            "name": "email",
            "in": "query",
            "style": "form",
            "schema": {
              "type": "string"
            }
          },
          {
            "name": "passwordToConfirm",
            "in": "query",
            "style": "form",
            "schema": {
              "type": "string"
            }
          }
        ],
        "responses": {
          "200": {
            "description": "Success"
          },
          "401": {
            "description": "Unauthorized",
            "content": {
              "text/plain": {
                "schema": {
                  "$ref": "#/components/schemas/ProblemDetails"
                }
              },
              "application/json": {
                "schema": {
                  "$ref": "#/components/schemas/ProblemDetails"
                }
              },
              "text/json": {
                "schema": {
                  "$ref": "#/components/schemas/ProblemDetails"
                }
              }
            }
          },
          "404": {
            "description": "Not Found",
            "content": {
              "text/plain": {
                "schema": {
                  "$ref": "#/components/schemas/ProblemDetails"
                }
              },
              "application/json": {
                "schema": {
                  "$ref": "#/components/schemas/ProblemDetails"
                }
              },
              "text/json": {
                "schema": {
                  "$ref": "#/components/schemas/ProblemDetails"
                }
              }
            }
          }
        }
      }
    },
    "/api/Account/ChangePassword": {
      "post": {
        "tags": [
          "Account"
        ],
        "parameters": [
          {
            "name": "oldpass",
            "in": "query",
            "style": "form",
            "schema": {
              "type": "string"
            }
          },
          {
            "name": "NewPass",
            "in": "query",
            "style": "form",
            "schema": {
              "type": "string"
            }
          },
          {
            "name": "confirmednewpass",
            "in": "query",
            "style": "form",
            "schema": {
              "type": "string"
            }
          }
        ],
        "responses": {
          "200": {
            "description": "Success"
          },
          "401": {
            "description": "Unauthorized",
            "content": {
              "text/plain": {
                "schema": {
                  "$ref": "#/components/schemas/ProblemDetails"
                }
              },
              "application/json": {
                "schema": {
                  "$ref": "#/components/schemas/ProblemDetails"
                }
              },
              "text/json": {
                "schema": {
                  "$ref": "#/components/schemas/ProblemDetails"
                }
              }
            }
          },
          "404": {
            "description": "Not Found",
            "content": {
              "text/plain": {
                "schema": {
                  "$ref": "#/components/schemas/ProblemDetails"
                }
              },
              "application/json": {
                "schema": {
                  "$ref": "#/components/schemas/ProblemDetails"
                }
              },
              "text/json": {
                "schema": {
                  "$ref": "#/components/schemas/ProblemDetails"
                }
              }
            }
          },
          "500": {
            "description": "Server Error"
          }
        }
      }
    },
    "/api/Account/ForgetPassword": {
      "get": {
        "tags": [
          "Account"
        ],
        "parameters": [
          {
            "name": "email",
            "in": "query",
            "style": "form",
            "schema": {
              "type": "string"
            }
          }
        ],
        "responses": {
          "400": {
            "description": "Bad Request",
            "content": {
              "text/plain": {
                "schema": {
                  "$ref": "#/components/schemas/ProblemDetails"
                }
              },
              "application/json": {
                "schema": {
                  "$ref": "#/components/schemas/ProblemDetails"
                }
              },
              "text/json": {
                "schema": {
                  "$ref": "#/components/schemas/ProblemDetails"
                }
              }
            }
          }
        }
      }
    },
    "/api/Account/SetNewPassword": {
      "put": {
        "tags": [
          "Account"
        ],
        "operationId": "SetNewPassword",
        "requestBody": {
          "content": {
            "application/json": {
              "schema": {
                "$ref": "#/components/schemas/ReSetPasswordDTO"
              }
            },
            "text/json": {
              "schema": {
                "$ref": "#/components/schemas/ReSetPasswordDTO"
              }
            },
            "application/*+json": {
              "schema": {
                "$ref": "#/components/schemas/ReSetPasswordDTO"
              }
            }
          }
        },
        "responses": {
          "400": {
            "description": "Bad Request",
            "content": {
              "text/plain": {
                "schema": {
                  "$ref": "#/components/schemas/ProblemDetails"
                }
              },
              "application/json": {
                "schema": {
                  "$ref": "#/components/schemas/ProblemDetails"
                }
              },
              "text/json": {
                "schema": {
                  "$ref": "#/components/schemas/ProblemDetails"
                }
              }
            }
          },
          "404": {
            "description": "Not Found",
            "content": {
              "text/plain": {
                "schema": {
                  "$ref": "#/components/schemas/ProblemDetails"
                }
              },
              "application/json": {
                "schema": {
                  "$ref": "#/components/schemas/ProblemDetails"
                }
              },
              "text/json": {
                "schema": {
                  "$ref": "#/components/schemas/ProblemDetails"
                }
              }
            }
          },
          "200": {
            "description": "Success"
          },
          "500": {
            "description": "Server Error"
          }
        }
      }
    },
    "/api/Cart/AddToCart": {
      "post": {
        "tags": [
          "Cart"
        ],
        "requestBody": {
          "content": {
            "application/json": {
              "schema": {
                "$ref": "#/components/schemas/AddProductCartDTO"
              }
            },
            "text/json": {
              "schema": {
                "$ref": "#/components/schemas/AddProductCartDTO"
              }
            },
            "application/*+json": {
              "schema": {
                "$ref": "#/components/schemas/AddProductCartDTO"
              }
            }
          }
        },
        "responses": {
          "200": {
            "description": "Success"
          },
          "400": {
            "description": "Bad Request",
            "content": {
              "text/plain": {
                "schema": {
                  "$ref": "#/components/schemas/ProblemDetails"
                }
              },
              "application/json": {
                "schema": {
                  "$ref": "#/components/schemas/ProblemDetails"
                }
              },
              "text/json": {
                "schema": {
                  "$ref": "#/components/schemas/ProblemDetails"
                }
              }
            }
          },
          "404": {
            "description": "Not Found",
            "content": {
              "text/plain": {
                "schema": {
                  "$ref": "#/components/schemas/ProblemDetails"
                }
              },
              "application/json": {
                "schema": {
                  "$ref": "#/components/schemas/ProblemDetails"
                }
              },
              "text/json": {
                "schema": {
                  "$ref": "#/components/schemas/ProblemDetails"
                }
              }
            }
          },
          "401": {
            "description": "Unauthorized",
            "content": {
              "text/plain": {
                "schema": {
                  "$ref": "#/components/schemas/ProblemDetails"
                }
              },
              "application/json": {
                "schema": {
                  "$ref": "#/components/schemas/ProblemDetails"
                }
              },
              "text/json": {
                "schema": {
                  "$ref": "#/components/schemas/ProblemDetails"
                }
              }
            }
          }
        }
      }
    },
    "/api/Cart/DeleteFromCart": {
      "delete": {
        "tags": [
          "Cart"
        ],
        "parameters": [
          {
            "name": "productID",
            "in": "query",
            "style": "form",
            "schema": {
              "type": "string"
            }
          }
        ],
        "responses": {
          "200": {
            "description": "Success"
          },
          "400": {
            "description": "Bad Request",
            "content": {
              "text/plain": {
                "schema": {
                  "$ref": "#/components/schemas/ProblemDetails"
                }
              },
              "application/json": {
                "schema": {
                  "$ref": "#/components/schemas/ProblemDetails"
                }
              },
              "text/json": {
                "schema": {
                  "$ref": "#/components/schemas/ProblemDetails"
                }
              }
            }
          },
          "404": {
            "description": "Not Found",
            "content": {
              "text/plain": {
                "schema": {
                  "$ref": "#/components/schemas/ProblemDetails"
                }
              },
              "application/json": {
                "schema": {
                  "$ref": "#/components/schemas/ProblemDetails"
                }
              },
              "text/json": {
                "schema": {
                  "$ref": "#/components/schemas/ProblemDetails"
                }
              }
            }
          },
          "401": {
            "description": "Unauthorized",
            "content": {
              "text/plain": {
                "schema": {
                  "$ref": "#/components/schemas/ProblemDetails"
                }
              },
              "application/json": {
                "schema": {
                  "$ref": "#/components/schemas/ProblemDetails"
                }
              },
              "text/json": {
                "schema": {
                  "$ref": "#/components/schemas/ProblemDetails"
                }
              }
            }
          }
        }
      }
    },
    "/api/Cart": {
      "get": {
        "tags": [
          "Cart"
        ],
        "responses": {
          "200": {
            "description": "Success"
          },
          "401": {
            "description": "Unauthorized",
            "content": {
              "text/plain": {
                "schema": {
                  "$ref": "#/components/schemas/ProblemDetails"
                }
              },
              "application/json": {
                "schema": {
                  "$ref": "#/components/schemas/ProblemDetails"
                }
              },
              "text/json": {
                "schema": {
                  "$ref": "#/components/schemas/ProblemDetails"
                }
              }
            }
          },
          "404": {
            "description": "Not Found",
            "content": {
              "text/plain": {
                "schema": {
                  "$ref": "#/components/schemas/ProblemDetails"
                }
              },
              "application/json": {
                "schema": {
                  "$ref": "#/components/schemas/ProblemDetails"
                }
              },
              "text/json": {
                "schema": {
                  "$ref": "#/components/schemas/ProblemDetails"
                }
              }
            }
          }
        }
      }
    },
    "/api/Categories/GetAllCategories": {
      "get": {
        "tags": [
          "Categories"
        ],
        "responses": {
          "200": {
            "description": "Success"
          },
          "404": {
            "description": "Not Found",
            "content": {
              "text/plain": {
                "schema": {
                  "$ref": "#/components/schemas/ProblemDetails"
                }
              },
              "application/json": {
                "schema": {
                  "$ref": "#/components/schemas/ProblemDetails"
                }
              },
              "text/json": {
                "schema": {
                  "$ref": "#/components/schemas/ProblemDetails"
                }
              }
            }
          }
        }
      }
    },
    "/api/Categories": {
      "post": {
        "tags": [
          "Categories"
        ],
        "requestBody": {
          "content": {
            "application/json": {
              "schema": {
                "$ref": "#/components/schemas/CategoryDTO"
              }
            },
            "text/json": {
              "schema": {
                "$ref": "#/components/schemas/CategoryDTO"
              }
            },
            "application/*+json": {
              "schema": {
                "$ref": "#/components/schemas/CategoryDTO"
              }
            }
          }
        },
        "responses": {
          "200": {
            "description": "Success"
          },
          "500": {
            "description": "Server Error"
          }
        }
      }
    },
    "/api/Contact/ContactUs": {
      "post": {
        "tags": [
          "Contact"
        ],
        "requestBody": {
          "content": {
            "application/json": {
              "schema": {
                "$ref": "#/components/schemas/ContactUsDTO"
              }
            },
            "text/json": {
              "schema": {
                "$ref": "#/components/schemas/ContactUsDTO"
              }
            },
            "application/*+json": {
              "schema": {
                "$ref": "#/components/schemas/ContactUsDTO"
              }
            }
          }
        },
        "responses": {
          "200": {
            "description": "Success"
          },
          "400": {
            "description": "Bad Request",
            "content": {
              "text/plain": {
                "schema": {
                  "$ref": "#/components/schemas/ProblemDetails"
                }
              },
              "application/json": {
                "schema": {
                  "$ref": "#/components/schemas/ProblemDetails"
                }
              },
              "text/json": {
                "schema": {
                  "$ref": "#/components/schemas/ProblemDetails"
                }
              }
            }
          }
        }
      }
    },
    "/api/Produts/All": {
      "get": {
        "tags": [
          "Product"
        ],
        "responses": {
          "200": {
            "description": "Success"
          },
          "404": {
            "description": "Not Found",
            "content": {
              "text/plain": {
                "schema": {
                  "$ref": "#/components/schemas/ProblemDetails"
                }
              },
              "application/json": {
                "schema": {
                  "$ref": "#/components/schemas/ProblemDetails"
                }
              },
              "text/json": {
                "schema": {
                  "$ref": "#/components/schemas/ProblemDetails"
                }
              }
            }
          }
        }
      }
    },
    "/api/Produts/Add": {
      "post": {
        "tags": [
          "Product"
        ],
        "requestBody": {
          "content": {
            "multipart/form-data": {
              "schema": {
                "type": "object",
                "properties": {
                  "Name": {
                    "type": "string"
                  },
                  "categoryId": {
                    "type": "integer",
                    "format": "int32"
                  },
                  "Description": {
                    "type": "string"
                  },
                  "Price": {
                    "type": "number",
                    "format": "double"
                  },
                  "availInStock": {
                    "type": "integer",
                    "format": "int32"
                  },
                  "formFile": {
                    "type": "array",
                    "items": {
                      "type": "string",
                      "format": "binary"
                    }
                  }
                }
              },
              "encoding": {
                "Name": {
                  "style": "form"
                },
                "categoryId": {
                  "style": "form"
                },
                "Description": {
                  "style": "form"
                },
                "Price": {
                  "style": "form"
                },
                "availInStock": {
                  "style": "form"
                },
                "formFile": {
                  "style": "form"
                }
              }
            }
          }
        },
        "responses": {
          "201": {
            "description": "Created"
          },
          "500": {
            "description": "Server Error"
          },
          "400": {
            "description": "Bad Request",
            "content": {
              "text/plain": {
                "schema": {
                  "$ref": "#/components/schemas/ProblemDetails"
                }
              },
              "application/json": {
                "schema": {
                  "$ref": "#/components/schemas/ProblemDetails"
                }
              },
              "text/json": {
                "schema": {
                  "$ref": "#/components/schemas/ProblemDetails"
                }
              }
            }
          },
          "401": {
            "description": "Unauthorized",
            "content": {
              "text/plain": {
                "schema": {
                  "$ref": "#/components/schemas/ProblemDetails"
                }
              },
              "application/json": {
                "schema": {
                  "$ref": "#/components/schemas/ProblemDetails"
                }
              },
              "text/json": {
                "schema": {
                  "$ref": "#/components/schemas/ProblemDetails"
                }
              }
            }
          }
        }
      }
    },
    "/api/Produts/Prod/{productId}": {
      "get": {
        "tags": [
          "Product"
        ],
        "operationId": "FindProduct",
        "parameters": [
          {
            "name": "productId",
            "in": "path",
            "required": true,
            "style": "simple",
            "schema": {
              "type": "string",
              "format": "uuid"
            }
          }
        ],
        "responses": {
          "200": {
            "description": "Success"
          },
          "400": {
            "description": "Bad Request",
            "content": {
              "text/plain": {
                "schema": {
                  "$ref": "#/components/schemas/ProblemDetails"
                }
              },
              "application/json": {
                "schema": {
                  "$ref": "#/components/schemas/ProblemDetails"
                }
              },
              "text/json": {
                "schema": {
                  "$ref": "#/components/schemas/ProblemDetails"
                }
              }
            }
          },
          "404": {
            "description": "Not Found",
            "content": {
              "text/plain": {
                "schema": {
                  "$ref": "#/components/schemas/ProblemDetails"
                }
              },
              "application/json": {
                "schema": {
                  "$ref": "#/components/schemas/ProblemDetails"
                }
              },
              "text/json": {
                "schema": {
                  "$ref": "#/components/schemas/ProblemDetails"
                }
              }
            }
          }
        }
      }
    },
    "/api/Produts/Category/{id}": {
      "get": {
        "tags": [
          "Product"
        ],
        "parameters": [
          {
            "name": "id",
            "in": "path",
            "required": true,
            "style": "simple",
            "schema": {
              "type": "integer",
              "format": "int32"
            }
          }
        ],
        "responses": {
          "200": {
            "description": "Success"
          },
          "400": {
            "description": "Bad Request",
            "content": {
              "text/plain": {
                "schema": {
                  "$ref": "#/components/schemas/ProblemDetails"
                }
              },
              "application/json": {
                "schema": {
                  "$ref": "#/components/schemas/ProblemDetails"
                }
              },
              "text/json": {
                "schema": {
                  "$ref": "#/components/schemas/ProblemDetails"
                }
              }
            }
          },
          "404": {
            "description": "Not Found",
            "content": {
              "text/plain": {
                "schema": {
                  "$ref": "#/components/schemas/ProblemDetails"
                }
              },
              "application/json": {
                "schema": {
                  "$ref": "#/components/schemas/ProblemDetails"
                }
              },
              "text/json": {
                "schema": {
                  "$ref": "#/components/schemas/ProblemDetails"
                }
              }
            }
          }
        }
      }
    },
    "/api/Produts/{Categoryname}": {
      "get": {
        "tags": [
          "Product"
        ],
        "parameters": [
          {
            "name": "Categoryname",
            "in": "path",
            "required": true,
            "style": "simple",
            "schema": {
              "type": "string"
            }
          }
        ],
        "responses": {
          "200": {
            "description": "Success"
          },
          "400": {
            "description": "Bad Request",
            "content": {
              "text/plain": {
                "schema": {
                  "$ref": "#/components/schemas/ProblemDetails"
                }
              },
              "application/json": {
                "schema": {
                  "$ref": "#/components/schemas/ProblemDetails"
                }
              },
              "text/json": {
                "schema": {
                  "$ref": "#/components/schemas/ProblemDetails"
                }
              }
            }
          },
          "404": {
            "description": "Not Found",
            "content": {
              "text/plain": {
                "schema": {
                  "$ref": "#/components/schemas/ProblemDetails"
                }
              },
              "application/json": {
                "schema": {
                  "$ref": "#/components/schemas/ProblemDetails"
                }
              },
              "text/json": {
                "schema": {
                  "$ref": "#/components/schemas/ProblemDetails"
                }
              }
            }
          }
        }
      }
    },
    "/api/Produts/ExploreProducts": {
      "get": {
        "tags": [
          "Product"
        ],
        "responses": {
          "200": {
            "description": "Success"
          },
          "404": {
            "description": "Not Found",
            "content": {
              "text/plain": {
                "schema": {
                  "$ref": "#/components/schemas/ProblemDetails"
                }
              },
              "application/json": {
                "schema": {
                  "$ref": "#/components/schemas/ProblemDetails"
                }
              },
              "text/json": {
                "schema": {
                  "$ref": "#/components/schemas/ProblemDetails"
                }
              }
            }
          }
        }
      }
    },
    "/api/Produts/JustForYou": {
      "get": {
        "tags": [
          "Product"
        ],
        "responses": {
          "200": {
            "description": "Success"
          },
          "401": {
            "description": "Unauthorized",
            "content": {
              "text/plain": {
                "schema": {
                  "$ref": "#/components/schemas/ProblemDetails"
                }
              },
              "application/json": {
                "schema": {
                  "$ref": "#/components/schemas/ProblemDetails"
                }
              },
              "text/json": {
                "schema": {
                  "$ref": "#/components/schemas/ProblemDetails"
                }
              }
            }
          },
          "404": {
            "description": "Not Found",
            "content": {
              "text/plain": {
                "schema": {
                  "$ref": "#/components/schemas/ProblemDetails"
                }
              },
              "application/json": {
                "schema": {
                  "$ref": "#/components/schemas/ProblemDetails"
                }
              },
              "text/json": {
                "schema": {
                  "$ref": "#/components/schemas/ProblemDetails"
                }
              }
            }
          }
        }
      }
    },
    "/api/Reviews/AddReview": {
      "post": {
        "tags": [
          "Reviews"
        ],
        "requestBody": {
          "content": {
            "application/json": {
              "schema": {
                "$ref": "#/components/schemas/AddReviewDTO"
              }
            },
            "text/json": {
              "schema": {
                "$ref": "#/components/schemas/AddReviewDTO"
              }
            },
            "application/*+json": {
              "schema": {
                "$ref": "#/components/schemas/AddReviewDTO"
              }
            }
          }
        },
        "responses": {
          "200": {
            "description": "Success"
          },
          "400": {
            "description": "Bad Request",
            "content": {
              "text/plain": {
                "schema": {
                  "$ref": "#/components/schemas/ProblemDetails"
                }
              },
              "application/json": {
                "schema": {
                  "$ref": "#/components/schemas/ProblemDetails"
                }
              },
              "text/json": {
                "schema": {
                  "$ref": "#/components/schemas/ProblemDetails"
                }
              }
            }
          },
          "401": {
            "description": "Unauthorized",
            "content": {
              "text/plain": {
                "schema": {
                  "$ref": "#/components/schemas/ProblemDetails"
                }
              },
              "application/json": {
                "schema": {
                  "$ref": "#/components/schemas/ProblemDetails"
                }
              },
              "text/json": {
                "schema": {
                  "$ref": "#/components/schemas/ProblemDetails"
                }
              }
            }
          },
          "500": {
            "description": "Server Error"
          }
        }
      }
    },
    "/api/Reviews/UserReview": {
      "get": {
        "tags": [
          "Reviews"
        ],
        "parameters": [
          {
            "name": "ProductID",
            "in": "query",
            "style": "form",
            "schema": {
              "type": "string"
            }
          }
        ],
        "responses": {
          "200": {
            "description": "Success"
          },
          "400": {
            "description": "Bad Request",
            "content": {
              "text/plain": {
                "schema": {
                  "$ref": "#/components/schemas/ProblemDetails"
                }
              },
              "application/json": {
                "schema": {
                  "$ref": "#/components/schemas/ProblemDetails"
                }
              },
              "text/json": {
                "schema": {
                  "$ref": "#/components/schemas/ProblemDetails"
                }
              }
            }
          },
          "401": {
            "description": "Unauthorized",
            "content": {
              "text/plain": {
                "schema": {
                  "$ref": "#/components/schemas/ProblemDetails"
                }
              },
              "application/json": {
                "schema": {
                  "$ref": "#/components/schemas/ProblemDetails"
                }
              },
              "text/json": {
                "schema": {
                  "$ref": "#/components/schemas/ProblemDetails"
                }
              }
            }
          },
          "500": {
            "description": "Server Error"
          }
        }
      }
    },
    "/api/Reviews/UpdateReview": {
      "put": {
        "tags": [
          "Reviews"
        ],
        "requestBody": {
          "content": {
            "application/json": {
              "schema": {
                "$ref": "#/components/schemas/AddReviewDTO"
              }
            },
            "text/json": {
              "schema": {
                "$ref": "#/components/schemas/AddReviewDTO"
              }
            },
            "application/*+json": {
              "schema": {
                "$ref": "#/components/schemas/AddReviewDTO"
              }
            }
          }
        },
        "responses": {
          "200": {
            "description": "Success"
          },
          "400": {
            "description": "Bad Request",
            "content": {
              "text/plain": {
                "schema": {
                  "$ref": "#/components/schemas/ProblemDetails"
                }
              },
              "application/json": {
                "schema": {
                  "$ref": "#/components/schemas/ProblemDetails"
                }
              },
              "text/json": {
                "schema": {
                  "$ref": "#/components/schemas/ProblemDetails"
                }
              }
            }
          },
          "401": {
            "description": "Unauthorized",
            "content": {
              "text/plain": {
                "schema": {
                  "$ref": "#/components/schemas/ProblemDetails"
                }
              },
              "application/json": {
                "schema": {
                  "$ref": "#/components/schemas/ProblemDetails"
                }
              },
              "text/json": {
                "schema": {
                  "$ref": "#/components/schemas/ProblemDetails"
                }
              }
            }
          },
          "500": {
            "description": "Server Error"
          }
        }
      }
    },
    "/api/Reviews/DeleteReview": {
      "delete": {
        "tags": [
          "Reviews"
        ],
        "parameters": [
          {
            "name": "ProductID",
            "in": "query",
            "style": "form",
            "schema": {
              "type": "string"
            }
          }
        ],
        "responses": {
          "200": {
            "description": "Success"
          },
          "400": {
            "description": "Bad Request",
            "content": {
              "text/plain": {
                "schema": {
                  "$ref": "#/components/schemas/ProblemDetails"
                }
              },
              "application/json": {
                "schema": {
                  "$ref": "#/components/schemas/ProblemDetails"
                }
              },
              "text/json": {
                "schema": {
                  "$ref": "#/components/schemas/ProblemDetails"
                }
              }
            }
          },
          "401": {
            "description": "Unauthorized",
            "content": {
              "text/plain": {
                "schema": {
                  "$ref": "#/components/schemas/ProblemDetails"
                }
              },
              "application/json": {
                "schema": {
                  "$ref": "#/components/schemas/ProblemDetails"
                }
              },
              "text/json": {
                "schema": {
                  "$ref": "#/components/schemas/ProblemDetails"
                }
              }
            }
          },
          "500": {
            "description": "Server Error"
          }
        }
      }
    },
    "/api/WishList/Add/{productID}": {
      "post": {
        "tags": [
          "WishList"
        ],
        "parameters": [
          {
            "name": "productID",
            "in": "path",
            "required": true,
            "style": "simple",
            "schema": {
              "type": "string"
            }
          }
        ],
        "responses": {
          "200": {
            "description": "Success"
          },
          "400": {
            "description": "Bad Request",
            "content": {
              "text/plain": {
                "schema": {
                  "$ref": "#/components/schemas/ProblemDetails"
                }
              },
              "application/json": {
                "schema": {
                  "$ref": "#/components/schemas/ProblemDetails"
                }
              },
              "text/json": {
                "schema": {
                  "$ref": "#/components/schemas/ProblemDetails"
                }
              }
            }
          },
          "401": {
            "description": "Unauthorized",
            "content": {
              "text/plain": {
                "schema": {
                  "$ref": "#/components/schemas/ProblemDetails"
                }
              },
              "application/json": {
                "schema": {
                  "$ref": "#/components/schemas/ProblemDetails"
                }
              },
              "text/json": {
                "schema": {
                  "$ref": "#/components/schemas/ProblemDetails"
                }
              }
            }
          },
          "500": {
            "description": "Server Error"
          }
        }
      }
    },
    "/api/WishList/Delete/{productID}": {
      "delete": {
        "tags": [
          "WishList"
        ],
        "parameters": [
          {
            "name": "productID",
            "in": "path",
            "required": true,
            "style": "simple",
            "schema": {
              "type": "string"
            }
          }
        ],
        "responses": {
          "200": {
            "description": "Success"
          },
          "400": {
            "description": "Bad Request",
            "content": {
              "text/plain": {
                "schema": {
                  "$ref": "#/components/schemas/ProblemDetails"
                }
              },
              "application/json": {
                "schema": {
                  "$ref": "#/components/schemas/ProblemDetails"
                }
              },
              "text/json": {
                "schema": {
                  "$ref": "#/components/schemas/ProblemDetails"
                }
              }
            }
          },
          "401": {
            "description": "Unauthorized",
            "content": {
              "text/plain": {
                "schema": {
                  "$ref": "#/components/schemas/ProblemDetails"
                }
              },
              "application/json": {
                "schema": {
                  "$ref": "#/components/schemas/ProblemDetails"
                }
              },
              "text/json": {
                "schema": {
                  "$ref": "#/components/schemas/ProblemDetails"
                }
              }
            }
          },
          "500": {
            "description": "Server Error"
          }
        }
      }
    },
    "/api/WishList": {
      "get": {
        "tags": [
          "WishList"
        ],
        "responses": {
          "200": {
            "description": "Success"
          },
          "401": {
            "description": "Unauthorized",
            "content": {
              "text/plain": {
                "schema": {
                  "$ref": "#/components/schemas/ProblemDetails"
                }
              },
              "application/json": {
                "schema": {
                  "$ref": "#/components/schemas/ProblemDetails"
                }
              },
              "text/json": {
                "schema": {
                  "$ref": "#/components/schemas/ProblemDetails"
                }
              }
            }
          },
          "500": {
            "description": "Server Error"
          },
          "404": {
            "description": "Not Found",
            "content": {
              "text/plain": {
                "schema": {
                  "$ref": "#/components/schemas/ProblemDetails"
                }
              },
              "application/json": {
                "schema": {
                  "$ref": "#/components/schemas/ProblemDetails"
                }
              },
              "text/json": {
                "schema": {
                  "$ref": "#/components/schemas/ProblemDetails"
                }
              }
            }
          }
        }
      }
    }
  },
  "components": {
    "schemas": {
      "AddProductCartDTO": {
        "type": "object",
        "properties": {
          "productId": {
            "type": "string",
            "nullable": true
          },
          "quantity": {
            "type": "integer",
            "format": "int32"
          }
        },
        "additionalProperties": false
      },
      "AddReviewDTO": {
        "type": "object",
        "properties": {
          "productID": {
            "type": "string",
            "nullable": true
          },
          "reviewText": {
            "type": "string",
            "nullable": true
          },
          "stars": {
            "maximum": 5,
            "minimum": 0,
            "type": "number",
            "format": "double"
          }
        },
        "additionalProperties": false
      },
      "CategoryDTO": {
        "type": "object",
        "properties": {
          "name": {
            "type": "string",
            "nullable": true
          }
        },
        "additionalProperties": false
      },
      "ChangeUserInfoDTO": {
        "type": "object",
        "properties": {
          "passwordToConfirm": {
            "type": "string",
            "nullable": true
          },
          "address": {
            "type": "string",
            "nullable": true
          },
          "fullName": {
            "type": "string",
            "nullable": true
          }
        },
        "additionalProperties": false
      },
      "ContactUsDTO": {
        "type": "object",
        "properties": {
          "name": {
            "type": "string",
            "nullable": true
          },
          "email": {
            "type": "string",
            "nullable": true
          },
          "phone": {
            "type": "string",
            "nullable": true
          },
          "subject": {
            "type": "string",
            "nullable": true
          },
          "message": {
            "type": "string",
            "nullable": true
          }
        },
        "additionalProperties": false
      },
      "LoginDTO": {
        "type": "object",
        "properties": {
          "email": {
            "type": "string",
            "nullable": true
          },
          "password": {
            "type": "string",
            "format": "password",
            "nullable": true
          }
        },
        "additionalProperties": false
      },
      "ProblemDetails": {
        "type": "object",
        "properties": {
          "type": {
            "type": "string",
            "nullable": true
          },
          "title": {
            "type": "string",
            "nullable": true
          },
          "status": {
            "type": "integer",
            "format": "int32",
            "nullable": true
          },
          "detail": {
            "type": "string",
            "nullable": true
          },
          "instance": {
            "type": "string",
            "nullable": true
          }
        },
        "additionalProperties": { }
      },
      "ReSetPasswordDTO": {
        "type": "object",
        "properties": {
          "token": {
            "type": "string",
            "nullable": true
          },
          "email": {
            "type": "string",
            "nullable": true
          },
          "newPassword": {
            "type": "string",
            "nullable": true
          },
          "confirmNewPassword": {
            "type": "string",
            "nullable": true
          }
        },
        "additionalProperties": false
      },
      "RegisterDTO": {
        "type": "object",
        "properties": {
          "fullName": {
            "type": "string",
            "nullable": true
          },
          "email": {
            "type": "string",
            "nullable": true
          },
          "password": {
            "type": "string",
            "nullable": true
          },
          "confirmPassword": {
            "type": "string",
            "nullable": true
          },
          "address": {
            "type": "string",
            "nullable": true
          }
        },
        "additionalProperties": false
      }
    },
    "securitySchemes": {
      "Bearer": {
        "type": "http",
        "description": "Fill in the JWT token",
        "scheme": "Bearer",
        "bearerFormat": "JWT"
      }
    }
  },
  "security": [
    {
      "Bearer": [ ]
    }
  ]
}